ptscore/__init__.py
ptscore/manager.py
ptscore/storage/__init__.py
ptscore/storage/dynamodb.py
ptscore/storage/memorydb.py
ptscore/storage/redis.py
tests/__init__.py
tests/unit/__init__.py
tests/unit/test_manager.py
ptscore-0.1.4.dist-info/LICENSE
ptscore-0.1.4.dist-info/METADATA
ptscore-0.1.4.dist-info/WHEEL
ptscore-0.1.4.dist-info/top_level.txt
ptscore-0.1.4.dist-info/RECORD
