Metadata-Version: 2.1
Name: ptscore
Version: 0.1.4
Summary: PassTheSecret core library containing back-end code for encryption and storage of secrets.
Home-page: https://github.com/passthesecret/passthesecret-core
Author: Caesar Kabalan
Author-email: caesar.kabalan@gmail.com
License: UNKNOWN
Platform: UNKNOWN
Classifier: Programming Language :: Python :: 3
Classifier: Development Status :: 3 - Alpha
Classifier: License :: OSI Approved :: GNU General Public License v3 or later (GPLv3+)
Classifier: Operating System :: OS Independent
Requires-Python: >=3.7
